pandalib/__init__.py
pandalib-0.2.3.dist-info/METADATA
pandalib-0.2.3.dist-info/WHEEL
pandalib-0.2.3.dist-info/top_level.txt
pandalib-0.2.3.dist-info/RECORD
