Metadata-Version: 2.1
Name: pandalib
Version: 0.2.3
Summary: A python module to interact with the api of the popular agent pandabuy
Home-page: https://github.com/Galbaninoh/pandalib
Author: galbaninoh
Author-email: galbaninoh@galbaninoh.space
Requires-Dist: cloudscraper
